README.rst
badass.py
setup.py
badass.egg-info/PKG-INFO
badass.egg-info/SOURCES.txt
badass.egg-info/dependency_links.txt
badass.egg-info/top_level.txt