Metadata-Version: 1.1
Name: badass
Version: 3.14159
Summary: Betterize your Python.
Home-page: https://github.com/dfm/badass
Author: Dan Foreman-Mackey
Author-email: danfm@nyu.edu
License: UNKNOWN
Platform: UNKNOWN
Classifier: Development Status :: 5 - Production/Stable
Classifier: Operating System :: OS Independent
Classifier: Programming Language :: Python
